ppmutils/__init__.py
ppmutils/auth.py
ppmutils/fhir.py
ppmutils/p2md.py
ppmutils/ppm.py
ppmutils/qualtrics.py
ppmutils/tests/__init__.py
ppmutils/tests/runtests.py
ppmutils/tests/test_fhir.py
ppmutils/tests/test_ppm.py
ppm_utils-3.0.2.dist-info/METADATA
ppm_utils-3.0.2.dist-info/WHEEL
ppm_utils-3.0.2.dist-info/top_level.txt
ppm_utils-3.0.2.dist-info/RECORD
