Metadata-Version: 2.1
Name: ppm-utils
Version: 3.0.2
Home-page: https://github.com/hms-dbmi/ppm-utils
Author: HMS DBMI Tech-core
Author-email: dbmi-tech-core@hms.harvard.edu
License: Creative Commons Attribution-Noncommercial-Share Alike license
Classifier: Environment :: Web Environment
Classifier: Framework :: Django
Classifier: Framework :: Django :: 2.2
Classifier: Framework :: Django :: 3
Classifier: Framework :: Django :: 4
Classifier: Intended Audience :: Developers
Classifier: License :: OSI Approved :: BSD License
Classifier: Operating System :: OS Independent
Classifier: Programming Language :: Python
Classifier: Programming Language :: Python :: 3
Classifier: Programming Language :: Python :: 3.7
Classifier: Programming Language :: Python :: 3.8
Classifier: Programming Language :: Python :: 3.9
Classifier: Programming Language :: Python :: 3.10
Classifier: Topic :: Internet :: WWW/HTTP
Classifier: Topic :: Internet :: WWW/HTTP :: Dynamic Content
Requires-Dist: django
Requires-Dist: boto3
Requires-Dist: python-dateutil==2.*
Requires-Dist: fhirclient==4.2.*
Requires-Dist: requests==2.*
Requires-Dist: furl==2.*
Requires-Dist: requests-auth-aws-sigv4
Requires-Dist: google-api-python-client==2.*
Requires-Dist: typing-extensions
Provides-Extra: dev
Requires-Dist: pre-commit==2.*; extra == "dev"
Provides-Extra: test
Requires-Dist: pytest; extra == "test"
Requires-Dist: pytest-django; extra == "test"
Requires-Dist: coverage; extra == "test"
Requires-Dist: mock; extra == "test"
Requires-Dist: responses; extra == "test"
Requires-Dist: django-coverage; extra == "test"
